{"Alexandria":"http:\/\/ci.alexandria.va.us\/","Bedford":"http:\/\/www.bedfordva.gov","Bristol":"http:\/\/www.bristolva.org\/","Buena Vista":"http:\/\/www.buenavistavirginia.org\/","Charlottesville":"http:\/\/www.charlottesville.org\/","Chesapeake":"http:\/\/cityofchesapeake.net","Colonial Heights":"http:\/\/www.colonial-heights.com\/","Covington":"http:\/\/www.covington.va.us\/","Danville":"http:\/\/www.danville-va.gov\/home.asp","Emporia":"http:\/\/www.ci.emporia.va.us\/","Fairfax":"http:\/\/www.fairfaxva.gov","Falls Church":"http:\/\/www.ci.falls-church.va.us\/","Franklin":"http:\/\/www.ci.franklin.va.us\/","Fredericksburg":"http:\/\/www.fredericksburgva.gov\/","Hampton":"http:\/\/www.hampton.va.us\/","Harrisonburg":"http:\/\/www.ci.harrisonburg.va.us\/","Hopewell":"http:\/\/www.ci.hopewell.va.us\/","Lexington":"http:\/\/www.ci.lexington.va.us\/","Lynchburg":"http:\/\/www.lynchburgva.gov","Manassas":"http:\/\/www.manassascity.org\/","Manassas Park":"http:\/\/www.cityofmanassaspark.us\/","Martinsville":"http:\/\/www.ci.martinsville.va.us\/","Newport News":"http:\/\/www.nngov.com\/","Norfolk":"http:\/\/www.norfolk.gov\/","Norton":"http:\/\/www.nortonva.org\/","Petersburg":"http:\/\/www.petersburg-va.org\/","Poquoson":"http:\/\/www.ci.poquoson.va.us\/","Portsmouth":"http:\/\/www.ci.portsmouth.va.us\/","Radford":"http:\/\/www.radford.va.us\/","Richmond":"http:\/\/www.richmondgov.com\/","Roanoke":"http:\/\/www.roanokeva.gov\/","Salem":"http:\/\/www.ci.salem.va.us\/","Staunton":"http:\/\/www.staunton.va.us\/","Suffolk":"http:\/\/www.suffolk.va.us\/","Virginia Beach":"http:\/\/www.vbgov.com\/","Waynesboro":"http:\/\/www.waynesboro.va.us\/","Williamsburg":"http:\/\/www.ci.williamsburg.va.us\/","Winchester":"http:\/\/www.ci.winchester.va.us\/","Abingdon":"http:\/\/www.abingdon.com\/","Altavista":"http:\/\/www.ci.altavista.va.us\/","Ashland":"http:\/\/www.town.ashland.va.us\/","Big Stone Gap":"http:\/\/www.bigstonegap.org\/","Blacksburg":"http:\/\/www.blacksburg.va.us\/","Bowling Green":"http:\/\/www.townofbowlinggreen.com","Bridgewater":"http:\/\/www.town.bridgewater.va.us\/","Broadway":"http:\/\/www.town.broadway.va.us\/","Cape Charles":"http:\/\/capecharles.org\/","Chincoteague":"http:\/\/www.chincoteague-va.gov\/","Christiansburg":"http:\/\/www.christiansburg.org\/","Clifton Forge":"http:\/\/www.cliftonforge.org\/","Culpeper":"http:\/\/www.culpeper.to\/","Damascus":"http:\/\/www.damascus.org\/","Dayton":"http:\/\/www.daytonva.us","Dublin":"http:\/\/www.dublintown.org\/","Farmville":"http:\/\/farmvilleva.com\/","Front Royal":"http:\/\/www.frontroyalva.com\/","Grottoes":"http:\/\/www.ci.grottoes.va.us\/","Herndon":"http:\/\/www.town.herndon.va.us\/","Independence":"http:\/\/www.independenceva.com","La Crosse":"http:\/\/www.lacrosseva.org\/","Leesburg":"http:\/\/www.leesburgva.org\/","Louisa":"http:\/\/louisatown.org\/","Luray":"http:\/\/www.townofluray.com\/","Marion":"http:\/\/www.marionva.org\/","Middleburg":"http:\/\/www.middleburg.org\/","Mount Jackson":"http:\/\/mountjackson.com\/","New Market":"http:\/\/www.newmarketvirginia.com\/","Orange":"http:\/\/www.townoforangeva.org\/","Pearisburg":"http:\/\/www.pearisburg.org\/","Pulaski":"http:\/\/www.pulaskitown.org\/","Purcellville":"http:\/\/www.purcellvilleva.com\/","Rocky Mount":"http:\/\/www.rockymountva.org\/","Round Hill":"http:\/\/www.roundhillva.org\/","Rural Retreat":"http:\/\/www.townofruralretreat.com\/","Scottsville":"http:\/\/www.scottsville.org\/","Shenandoah":"http:\/\/www.townofshenandoah.com\/","Smithfield":"http:\/\/www.co.smithfield.va.us\/","South Boston":"http:\/\/www.southboston.com\/town\/","South Hill":"http:\/\/www.southhillva.org\/","Tazewell":"http:\/\/www.townoftazewell.org\/","Vienna":"http:\/\/www.ci.vienna.va.us\/","Vinton":"http:\/\/www.town.vinton.va.us\/","Warrenton":"http:\/\/www.townofwarrenton.com\/","West Point":"http:\/\/www.westpointvirginia.org\/","Wytheville":"http:\/\/townof.wytheville.org\/"}