{"Casper":"http:\/\/www.cityofcasperwy.com\/","Cheyenne":"http:\/\/www.cheyennecity.org\/","Douglas":"http:\/\/www.cityofdouglaswy.com\/","Evanston":"http:\/\/www.evanstonwy.org\/","Gillette":"http:\/\/www.ci.gillette.wy.us\/","Green River":"http:\/\/www.cityofgreenriver.org\/","Kemmerer":"http:\/\/www.kemmerer.org\/","Laramie":"http:\/\/www.ci.laramie.wy.us\/","Rawlins":"http:\/\/www.rawlins-wyoming.com\/","Riverton":"http:\/\/www.riverton.wyoming.com\/","Rock Springs":"http:\/\/www.rswy.net\/","Sheridan":"http:\/\/www.city-sheridan-wy.com\/","Torrington":"http:\/\/www.city-of-torrington.org\/","Worland":"http:\/\/www.cityofworland.org\/","Glendo":"http:\/\/glendowy.com","Jackson":"http:\/\/www.ci.jackson.wy.us\/","Pine Bluffs":"http:\/\/pinebluffs.org\/","Saratoga":"http:\/\/www.saratogawyo.com\/townhall\/","Thayne":"http:\/\/www.thayne-wy.com\/"}